{
  "trade": {
    "id": 18,
    "date": "2026-03-22 00:00",
    "side": "SHORT",
    "entry": 68744
  },
  "start_ms": 1774137600000,
  "candles_15m": [
    {
      "open_time": 1774137600000,
      "open": 68918.12,
      "high": 68951.7,
      "low": 68228.5,
      "close": 68690.35,
      "volume": 1104.05223,
      "close_time": 1774138499999,
      "quote_volume": 75712530.7654509,
      "num_trades": 175295,
      "taker_buy_volume": 525.41194,
      "taker_buy_quote_volume": 36032443.020291
    },
    {
      "open_time": 1774138500000,
      "open": 68690.36,
      "high": 69066.5,
      "low": 68658.0,
      "close": 68904.25,
      "volume": 500.73164,
      "close_time": 1774139399999,
      "quote_volume": 34475835.5623196,
      "num_trades": 77410,
      "taker_buy_volume": 261.58261,
      "taker_buy_quote_volume": 18011238.8334461
    },
    {
      "open_time": 1774139400000,
      "open": 68904.25,
      "high": 69155.86,
      "low": 68904.25,
      "close": 69069.68,
      "volume": 365.92911,
      "close_time": 1774140299999,
      "quote_volume": 25264109.2329226,
      "num_trades": 66510,
      "taker_buy_volume": 208.87375,
      "taker_buy_quote_volume": 14420511.2354648
    },
    {
      "open_time": 1774140300000,
      "open": 69069.68,
      "high": 69137.86,
      "low": 68779.08,
      "close": 68954.71,
      "volume": 190.45144,
      "close_time": 1774141199999,
      "quote_volume": 13130004.3853619,
      "num_trades": 48350,
      "taker_buy_volume": 105.51863,
      "taker_buy_quote_volume": 7274865.5997334
    },
    {
      "open_time": 1774141200000,
      "open": 68954.7,
      "high": 69100.0,
      "low": 68848.48,
      "close": 68971.82,
      "volume": 256.13185,
      "close_time": 1774142099999,
      "quote_volume": 17666574.0165393,
      "num_trades": 44610,
      "taker_buy_volume": 159.87441,
      "taker_buy_quote_volume": 11030245.0973773
    },
    {
      "open_time": 1774142100000,
      "open": 68971.81,
      "high": 69095.21,
      "low": 68901.28,
      "close": 69030.27,
      "volume": 126.71498,
      "close_time": 1774142999999,
      "quote_volume": 8746166.9660704,
      "num_trades": 34688,
      "taker_buy_volume": 48.10363,
      "taker_buy_quote_volume": 3319756.9631114
    },
    {
      "open_time": 1774143000000,
      "open": 69030.27,
      "high": 69080.0,
      "low": 68762.31,
      "close": 68845.5,
      "volume": 306.61105,
      "close_time": 1774143899999,
      "quote_volume": 21133037.166971,
      "num_trades": 39743,
      "taker_buy_volume": 133.99256,
      "taker_buy_quote_volume": 9237784.8540082
    },
    {
      "open_time": 1774143900000,
      "open": 68845.49,
      "high": 68990.64,
      "low": 68845.49,
      "close": 68962.4,
      "volume": 120.09863,
      "close_time": 1774144799999,
      "quote_volume": 8281180.4688849,
      "num_trades": 24504,
      "taker_buy_volume": 66.43938,
      "taker_buy_quote_volume": 4581173.0399171
    },
    {
      "open_time": 1774144800000,
      "open": 68962.4,
      "high": 69079.56,
      "low": 68951.21,
      "close": 69053.35,
      "volume": 83.78991,
      "close_time": 1774145699999,
      "quote_volume": 5782783.3261465,
      "num_trades": 28942,
      "taker_buy_volume": 53.63594,
      "taker_buy_quote_volume": 3701624.1254595
    },
    {
      "open_time": 1774145700000,
      "open": 69053.35,
      "high": 69411.1,
      "low": 68976.0,
      "close": 69357.07,
      "volume": 172.92827,
      "close_time": 1774146599999,
      "quote_volume": 11966918.8292348,
      "num_trades": 41327,
      "taker_buy_volume": 106.97496,
      "taker_buy_quote_volume": 7404196.7230754
    },
    {
      "open_time": 1774146600000,
      "open": 69357.07,
      "high": 69367.1,
      "low": 69207.65,
      "close": 69237.0,
      "volume": 133.29629,
      "close_time": 1774147499999,
      "quote_volume": 9231936.0609967,
      "num_trades": 36508,
      "taker_buy_volume": 66.08959,
      "taker_buy_quote_volume": 4577197.6017857
    },
    {
      "open_time": 1774147500000,
      "open": 69236.99,
      "high": 69366.26,
      "low": 69203.26,
      "close": 69278.12,
      "volume": 116.61391,
      "close_time": 1774148399999,
      "quote_volume": 8080817.186291,
      "num_trades": 30158,
      "taker_buy_volume": 68.83685,
      "taker_buy_quote_volume": 4770115.3223429
    },
    {
      "open_time": 1774148400000,
      "open": 69278.12,
      "high": 69342.75,
      "low": 69123.13,
      "close": 69308.01,
      "volume": 90.44478,
      "close_time": 1774149299999,
      "quote_volume": 6261433.2564545,
      "num_trades": 25542,
      "taker_buy_volume": 47.44388,
      "taker_buy_quote_volume": 3285075.5285946
    },
    {
      "open_time": 1774149300000,
      "open": 69308.02,
      "high": 69540.0,
      "low": 69261.41,
      "close": 69440.44,
      "volume": 285.89248,
      "close_time": 1774150199999,
      "quote_volume": 19830092.7559965,
      "num_trades": 33447,
      "taker_buy_volume": 144.73229,
      "taker_buy_quote_volume": 10036158.5516164
    },
    {
      "open_time": 1774150200000,
      "open": 69440.44,
      "high": 69588.79,
      "low": 69315.45,
      "close": 69355.6,
      "volume": 186.19149,
      "close_time": 1774151099999,
      "quote_volume": 12930259.8684116,
      "num_trades": 48118,
      "taker_buy_volume": 102.9516,
      "taker_buy_quote_volume": 7149838.4646727
    },
    {
      "open_time": 1774151100000,
      "open": 69355.6,
      "high": 69365.51,
      "low": 69277.23,
      "close": 69339.99,
      "volume": 108.61165,
      "close_time": 1774151999999,
      "quote_volume": 7529528.4490688,
      "num_trades": 19314,
      "taker_buy_volume": 48.98268,
      "taker_buy_quote_volume": 3395637.953971
    },
    {
      "open_time": 1774152000000,
      "open": 69340.0,
      "high": 69489.35,
      "low": 69309.98,
      "close": 69448.01,
      "volume": 204.99496,
      "close_time": 1774152899999,
      "quote_volume": 14225747.4019255,
      "num_trades": 23914,
      "taker_buy_volume": 161.19093,
      "taker_buy_quote_volume": 11185531.4664323
    },
    {
      "open_time": 1774152900000,
      "open": 69448.01,
      "high": 69526.85,
      "low": 69223.19,
      "close": 69260.0,
      "volume": 144.55476,
      "close_time": 1774153799999,
      "quote_volume": 10022699.5966461,
      "num_trades": 29891,
      "taker_buy_volume": 62.72538,
      "taker_buy_quote_volume": 4349361.7383642
    },
    {
      "open_time": 1774153800000,
      "open": 69260.0,
      "high": 69376.88,
      "low": 69215.89,
      "close": 69349.64,
      "volume": 108.41383,
      "close_time": 1774154699999,
      "quote_volume": 7513848.4675821,
      "num_trades": 19447,
      "taker_buy_volume": 72.08642,
      "taker_buy_quote_volume": 4996010.6678858
    },
    {
      "open_time": 1774154700000,
      "open": 69349.64,
      "high": 69408.27,
      "low": 69303.08,
      "close": 69358.0,
      "volume": 168.79346,
      "close_time": 1774155599999,
      "quote_volume": 11705449.3941758,
      "num_trades": 18906,
      "taker_buy_volume": 82.66842,
      "taker_buy_quote_volume": 5732802.2218362
    },
    {
      "open_time": 1774155600000,
      "open": 69358.0,
      "high": 69358.0,
      "low": 69219.87,
      "close": 69228.56,
      "volume": 97.67443,
      "close_time": 1774156499999,
      "quote_volume": 6766761.5715536,
      "num_trades": 19169,
      "taker_buy_volume": 28.10841,
      "taker_buy_quote_volume": 1947059.5502871
    },
    {
      "open_time": 1774156500000,
      "open": 69228.56,
      "high": 69271.83,
      "low": 69169.78,
      "close": 69175.82,
      "volume": 83.54301,
      "close_time": 1774157399999,
      "quote_volume": 5782634.9165864,
      "num_trades": 19144,
      "taker_buy_volume": 31.30849,
      "taker_buy_quote_volume": 2166901.3822091
    },
    {
      "open_time": 1774157400000,
      "open": 69175.83,
      "high": 69238.73,
      "low": 69150.0,
      "close": 69206.12,
      "volume": 74.73188,
      "close_time": 1774158299999,
      "quote_volume": 5171063.1433894,
      "num_trades": 15654,
      "taker_buy_volume": 39.7862,
      "taker_buy_quote_volume": 2752905.5503698
    },
    {
      "open_time": 1774158300000,
      "open": 69206.12,
      "high": 69263.45,
      "low": 69151.94,
      "close": 69153.41,
      "volume": 66.19202,
      "close_time": 1774159199999,
      "quote_volume": 4579663.7361323,
      "num_trades": 15493,
      "taker_buy_volume": 20.87781,
      "taker_buy_quote_volume": 1444558.1546854
    },
    {
      "open_time": 1774159200000,
      "open": 69153.41,
      "high": 69173.19,
      "low": 69059.87,
      "close": 69139.99,
      "volume": 210.4481,
      "close_time": 1774160099999,
      "quote_volume": 14548632.3556626,
      "num_trades": 24286,
      "taker_buy_volume": 110.97368,
      "taker_buy_quote_volume": 7671046.9198941
    },
    {
      "open_time": 1774160100000,
      "open": 69139.98,
      "high": 69236.3,
      "low": 69089.23,
      "close": 69236.29,
      "volume": 103.5965,
      "close_time": 1774160999999,
      "quote_volume": 7163443.1107678,
      "num_trades": 19174,
      "taker_buy_volume": 31.73219,
      "taker_buy_quote_volume": 2194470.7925048
    },
    {
      "open_time": 1774161000000,
      "open": 69236.29,
      "high": 69245.79,
      "low": 69174.0,
      "close": 69197.95,
      "volume": 29.89321,
      "close_time": 1774161899999,
      "quote_volume": 2068645.5051974,
      "num_trades": 14693,
      "taker_buy_volume": 16.23806,
      "taker_buy_quote_volume": 1123734.5619013
    },
    {
      "open_time": 1774161900000,
      "open": 69197.95,
      "high": 69203.5,
      "low": 69148.61,
      "close": 69164.06,
      "volume": 34.14738,
      "close_time": 1774162799999,
      "quote_volume": 2361944.638198,
      "num_trades": 13303,
      "taker_buy_volume": 14.30229,
      "taker_buy_quote_volume": 989285.3081779
    },
    {
      "open_time": 1774162800000,
      "open": 69164.06,
      "high": 69250.08,
      "low": 69128.63,
      "close": 69155.27,
      "volume": 104.83373,
      "close_time": 1774163699999,
      "quote_volume": 7251453.0909621,
      "num_trades": 17873,
      "taker_buy_volume": 32.10266,
      "taker_buy_quote_volume": 2220709.4270072
    },
    {
      "open_time": 1774163700000,
      "open": 69155.26,
      "high": 69200.0,
      "low": 69139.92,
      "close": 69181.62,
      "volume": 105.54887,
      "close_time": 1774164599999,
      "quote_volume": 7301221.3512927,
      "num_trades": 11077,
      "taker_buy_volume": 67.72658,
      "taker_buy_quote_volume": 4685160.5489784
    },
    {
      "open_time": 1774164600000,
      "open": 69181.63,
      "high": 69181.74,
      "low": 68926.19,
      "close": 68951.59,
      "volume": 126.61333,
      "close_time": 1774165499999,
      "quote_volume": 8741357.1011258,
      "num_trades": 35010,
      "taker_buy_volume": 40.95346,
      "taker_buy_quote_volume": 2827617.8151993
    },
    {
      "open_time": 1774165500000,
      "open": 68951.6,
      "high": 69088.0,
      "low": 68892.93,
      "close": 68919.38,
      "volume": 95.94708,
      "close_time": 1774166399999,
      "quote_volume": 6619515.8643394,
      "num_trades": 24227,
      "taker_buy_volume": 46.75531,
      "taker_buy_quote_volume": 3226207.6876044
    },
    {
      "open_time": 1774166400000,
      "open": 68919.37,
      "high": 68990.67,
      "low": 68720.06,
      "close": 68990.67,
      "volume": 238.58408,
      "close_time": 1774167299999,
      "quote_volume": 16426990.8987451,
      "num_trades": 39480,
      "taker_buy_volume": 128.61968,
      "taker_buy_quote_volume": 8856966.2822321
    },
    {
      "open_time": 1774167300000,
      "open": 68990.66,
      "high": 68990.67,
      "low": 68560.27,
      "close": 68624.01,
      "volume": 451.78372,
      "close_time": 1774168199999,
      "quote_volume": 31067285.2246578,
      "num_trades": 57087,
      "taker_buy_volume": 133.38546,
      "taker_buy_quote_volume": 9169795.2743066
    },
    {
      "open_time": 1774168200000,
      "open": 68624.0,
      "high": 68787.84,
      "low": 68523.96,
      "close": 68738.56,
      "volume": 296.15755,
      "close_time": 1774169099999,
      "quote_volume": 20329788.6031673,
      "num_trades": 37697,
      "taker_buy_volume": 115.864,
      "taker_buy_quote_volume": 7958739.8617792
    },
    {
      "open_time": 1774169100000,
      "open": 68738.55,
      "high": 68825.0,
      "low": 68694.31,
      "close": 68804.77,
      "volume": 67.25167,
      "close_time": 1774169999999,
      "quote_volume": 4624132.3365031,
      "num_trades": 16756,
      "taker_buy_volume": 33.99683,
      "taker_buy_quote_volume": 2337605.3735695
    },
    {
      "open_time": 1774170000000,
      "open": 68804.77,
      "high": 68881.19,
      "low": 68750.94,
      "close": 68873.38,
      "volume": 81.12297,
      "close_time": 1774170899999,
      "quote_volume": 5583257.4453167,
      "num_trades": 21487,
      "taker_buy_volume": 46.69103,
      "taker_buy_quote_volume": 3213475.8999979
    },
    {
      "open_time": 1774170900000,
      "open": 68873.37,
      "high": 68901.65,
      "low": 68587.78,
      "close": 68649.09,
      "volume": 177.61728,
      "close_time": 1774171799999,
      "quote_volume": 12207245.475365,
      "num_trades": 36150,
      "taker_buy_volume": 59.1161,
      "taker_buy_quote_volume": 4063198.1301253
    },
    {
      "open_time": 1774171800000,
      "open": 68649.09,
      "high": 68829.02,
      "low": 68644.58,
      "close": 68782.75,
      "volume": 69.66217,
      "close_time": 1774172699999,
      "quote_volume": 4787966.8677973,
      "num_trades": 22922,
      "taker_buy_volume": 43.49525,
      "taker_buy_quote_volume": 2989440.6840675
    },
    {
      "open_time": 1774172700000,
      "open": 68782.76,
      "high": 68847.83,
      "low": 68763.55,
      "close": 68826.2,
      "volume": 55.42521,
      "close_time": 1774173599999,
      "quote_volume": 3814110.5215805,
      "num_trades": 21251,
      "taker_buy_volume": 36.77443,
      "taker_buy_quote_volume": 2530760.6649705
    },
    {
      "open_time": 1774173600000,
      "open": 68826.21,
      "high": 68847.83,
      "low": 68680.0,
      "close": 68742.42,
      "volume": 141.72213,
      "close_time": 1774174499999,
      "quote_volume": 9745648.0279038,
      "num_trades": 23680,
      "taker_buy_volume": 64.82458,
      "taker_buy_quote_volume": 4457306.7521647
    },
    {
      "open_time": 1774174500000,
      "open": 68742.42,
      "high": 68744.55,
      "low": 68661.98,
      "close": 68731.27,
      "volume": 50.68614,
      "close_time": 1774175399999,
      "quote_volume": 3482925.8160131,
      "num_trades": 16642,
      "taker_buy_volume": 20.97075,
      "taker_buy_quote_volume": 1441120.3817344
    },
    {
      "open_time": 1774175400000,
      "open": 68731.27,
      "high": 68774.2,
      "low": 68585.91,
      "close": 68620.11,
      "volume": 87.03501,
      "close_time": 1774176299999,
      "quote_volume": 5976925.7951413,
      "num_trades": 26399,
      "taker_buy_volume": 40.4453,
      "taker_buy_quote_volume": 2778210.3987975
    },
    {
      "open_time": 1774176300000,
      "open": 68620.11,
      "high": 68687.19,
      "low": 68584.27,
      "close": 68648.17,
      "volume": 80.59018,
      "close_time": 1774177199999,
      "quote_volume": 5531344.8112653,
      "num_trades": 16695,
      "taker_buy_volume": 59.68319,
      "taker_buy_quote_volume": 4096259.8145269
    },
    {
      "open_time": 1774177200000,
      "open": 68648.16,
      "high": 68691.03,
      "low": 68568.5,
      "close": 68658.59,
      "volume": 53.68455,
      "close_time": 1774178099999,
      "quote_volume": 3684313.5722531,
      "num_trades": 20388,
      "taker_buy_volume": 32.52937,
      "taker_buy_quote_volume": 2232323.9549756
    },
    {
      "open_time": 1774178100000,
      "open": 68658.58,
      "high": 68682.36,
      "low": 68381.51,
      "close": 68419.89,
      "volume": 221.98126,
      "close_time": 1774178999999,
      "quote_volume": 15209126.2563948,
      "num_trades": 38630,
      "taker_buy_volume": 105.16641,
      "taker_buy_quote_volume": 7207736.6701293
    },
    {
      "open_time": 1774179000000,
      "open": 68419.9,
      "high": 68518.22,
      "low": 68287.0,
      "close": 68405.0,
      "volume": 182.86393,
      "close_time": 1774179899999,
      "quote_volume": 12508219.5949229,
      "num_trades": 46401,
      "taker_buy_volume": 69.25943,
      "taker_buy_quote_volume": 4738079.9070576
    },
    {
      "open_time": 1774179900000,
      "open": 68405.0,
      "high": 68424.27,
      "low": 68110.55,
      "close": 68217.95,
      "volume": 325.90186,
      "close_time": 1774180799999,
      "quote_volume": 22241861.9205506,
      "num_trades": 56532,
      "taker_buy_volume": 154.82971,
      "taker_buy_quote_volume": 10565582.6153269
    },
    {
      "open_time": 1774180800000,
      "open": 68217.94,
      "high": 68342.92,
      "low": 68199.04,
      "close": 68314.5,
      "volume": 112.72236,
      "close_time": 1774181699999,
      "quote_volume": 7695714.3167636,
      "num_trades": 37582,
      "taker_buy_volume": 73.59925,
      "taker_buy_quote_volume": 5024656.9916522
    },
    {
      "open_time": 1774181700000,
      "open": 68314.5,
      "high": 68763.18,
      "low": 68311.94,
      "close": 68662.51,
      "volume": 241.95545,
      "close_time": 1774182599999,
      "quote_volume": 16580292.2357924,
      "num_trades": 51146,
      "taker_buy_volume": 170.27562,
      "taker_buy_quote_volume": 11667730.1389084
    },
    {
      "open_time": 1774182600000,
      "open": 68662.51,
      "high": 68673.96,
      "low": 68592.96,
      "close": 68610.0,
      "volume": 66.05709,
      "close_time": 1774183499999,
      "quote_volume": 4533508.2273901,
      "num_trades": 22192,
      "taker_buy_volume": 37.90902,
      "taker_buy_quote_volume": 2601562.2504237
    },
    {
      "open_time": 1774183500000,
      "open": 68610.0,
      "high": 68693.82,
      "low": 68565.53,
      "close": 68654.83,
      "volume": 63.5081,
      "close_time": 1774184399999,
      "quote_volume": 4358175.371664,
      "num_trades": 27032,
      "taker_buy_volume": 33.12142,
      "taker_buy_quote_volume": 2272932.4316582
    },
    {
      "open_time": 1774184400000,
      "open": 68654.83,
      "high": 68957.24,
      "low": 68654.83,
      "close": 68815.32,
      "volume": 181.26769,
      "close_time": 1774185299999,
      "quote_volume": 12478703.1860716,
      "num_trades": 43056,
      "taker_buy_volume": 112.23118,
      "taker_buy_quote_volume": 7726112.9802078
    },
    {
      "open_time": 1774185300000,
      "open": 68815.32,
      "high": 68869.21,
      "low": 68750.0,
      "close": 68806.7,
      "volume": 134.14548,
      "close_time": 1774186199999,
      "quote_volume": 9230229.8039106,
      "num_trades": 23048,
      "taker_buy_volume": 65.19897,
      "taker_buy_quote_volume": 4486033.6497886
    },
    {
      "open_time": 1774186200000,
      "open": 68806.7,
      "high": 68849.85,
      "low": 68548.32,
      "close": 68627.92,
      "volume": 128.15071,
      "close_time": 1774187099999,
      "quote_volume": 8800714.7710584,
      "num_trades": 32727,
      "taker_buy_volume": 70.82407,
      "taker_buy_quote_volume": 4863679.3570858
    },
    {
      "open_time": 1774187100000,
      "open": 68627.92,
      "high": 68753.14,
      "low": 68592.0,
      "close": 68700.02,
      "volume": 104.50961,
      "close_time": 1774187999999,
      "quote_volume": 7178311.142289,
      "num_trades": 21906,
      "taker_buy_volume": 58.61981,
      "taker_buy_quote_volume": 4025889.2075123
    },
    {
      "open_time": 1774188000000,
      "open": 68700.02,
      "high": 68811.89,
      "low": 68542.1,
      "close": 68780.0,
      "volume": 136.92502,
      "close_time": 1774188899999,
      "quote_volume": 9401383.2313587,
      "num_trades": 36048,
      "taker_buy_volume": 62.59326,
      "taker_buy_quote_volume": 4297427.2933017
    },
    {
      "open_time": 1774188900000,
      "open": 68780.0,
      "high": 68900.0,
      "low": 68727.13,
      "close": 68839.99,
      "volume": 73.87696,
      "close_time": 1774189799999,
      "quote_volume": 5083102.2599939,
      "num_trades": 28156,
      "taker_buy_volume": 46.23584,
      "taker_buy_quote_volume": 3181191.8563573
    },
    {
      "open_time": 1774189800000,
      "open": 68840.0,
      "high": 68915.27,
      "low": 68782.49,
      "close": 68843.0,
      "volume": 69.37356,
      "close_time": 1774190699999,
      "quote_volume": 4776412.5202653,
      "num_trades": 24293,
      "taker_buy_volume": 37.12195,
      "taker_buy_quote_volume": 2555976.9025156
    },
    {
      "open_time": 1774190700000,
      "open": 68843.0,
      "high": 68843.01,
      "low": 68645.9,
      "close": 68711.66,
      "volume": 105.36922,
      "close_time": 1774191599999,
      "quote_volume": 7241032.1345243,
      "num_trades": 25067,
      "taker_buy_volume": 55.18515,
      "taker_buy_quote_volume": 3791965.581504
    },
    {
      "open_time": 1774191600000,
      "open": 68711.66,
      "high": 68940.0,
      "low": 68711.65,
      "close": 68904.24,
      "volume": 110.48153,
      "close_time": 1774192499999,
      "quote_volume": 7606136.4552824,
      "num_trades": 33476,
      "taker_buy_volume": 73.66777,
      "taker_buy_quote_volume": 5071626.9610278
    },
    {
      "open_time": 1774192500000,
      "open": 68904.24,
      "high": 69005.71,
      "low": 68809.43,
      "close": 68907.95,
      "volume": 133.24747,
      "close_time": 1774193399999,
      "quote_volume": 9183021.8520479,
      "num_trades": 36977,
      "taker_buy_volume": 88.20076,
      "taker_buy_quote_volume": 6079351.4636663
    },
    {
      "open_time": 1774193400000,
      "open": 68907.94,
      "high": 68910.8,
      "low": 68700.0,
      "close": 68803.1,
      "volume": 96.20216,
      "close_time": 1774194299999,
      "quote_volume": 6616577.1340442,
      "num_trades": 20127,
      "taker_buy_volume": 33.76133,
      "taker_buy_quote_volume": 2322416.0890595
    },
    {
      "open_time": 1774194300000,
      "open": 68803.1,
      "high": 68856.89,
      "low": 68753.18,
      "close": 68847.96,
      "volume": 51.2418,
      "close_time": 1774195199999,
      "quote_volume": 3526185.5310315,
      "num_trades": 14587,
      "taker_buy_volume": 30.31338,
      "taker_buy_quote_volume": 2085982.529946
    },
    {
      "open_time": 1774195200000,
      "open": 68847.97,
      "high": 68885.53,
      "low": 68770.0,
      "close": 68790.84,
      "volume": 65.82453,
      "close_time": 1774196099999,
      "quote_volume": 4530175.6841375,
      "num_trades": 19489,
      "taker_buy_volume": 27.54655,
      "taker_buy_quote_volume": 1895905.9190263
    },
    {
      "open_time": 1774196100000,
      "open": 68790.84,
      "high": 68814.31,
      "low": 68682.38,
      "close": 68715.09,
      "volume": 69.90297,
      "close_time": 1774196999999,
      "quote_volume": 4804868.8861121,
      "num_trades": 19751,
      "taker_buy_volume": 24.43006,
      "taker_buy_quote_volume": 1679127.3399022
    },
    {
      "open_time": 1774197000000,
      "open": 68715.09,
      "high": 68781.73,
      "low": 68665.62,
      "close": 68733.34,
      "volume": 79.24303,
      "close_time": 1774197899999,
      "quote_volume": 5445435.8397055,
      "num_trades": 16550,
      "taker_buy_volume": 48.50113,
      "taker_buy_quote_volume": 3333013.6796414
    },
    {
      "open_time": 1774197900000,
      "open": 68733.35,
      "high": 68848.9,
      "low": 68733.34,
      "close": 68805.58,
      "volume": 43.27982,
      "close_time": 1774198799999,
      "quote_volume": 2978240.4049047,
      "num_trades": 11195,
      "taker_buy_volume": 27.94913,
      "taker_buy_quote_volume": 1923224.9944335
    },
    {
      "open_time": 1774198800000,
      "open": 68805.58,
      "high": 68834.34,
      "low": 68739.76,
      "close": 68823.98,
      "volume": 38.36726,
      "close_time": 1774199699999,
      "quote_volume": 2639663.7863683,
      "num_trades": 15178,
      "taker_buy_volume": 15.9746,
      "taker_buy_quote_volume": 1099102.2121888
    },
    {
      "open_time": 1774199700000,
      "open": 68823.99,
      "high": 68848.32,
      "low": 68759.04,
      "close": 68810.33,
      "volume": 58.56919,
      "close_time": 1774200599999,
      "quote_volume": 4030343.7118735,
      "num_trades": 18918,
      "taker_buy_volume": 28.34496,
      "taker_buy_quote_volume": 1950595.979736
    },
    {
      "open_time": 1774200600000,
      "open": 68810.33,
      "high": 68824.99,
      "low": 68665.34,
      "close": 68671.02,
      "volume": 94.05778,
      "close_time": 1774201499999,
      "quote_volume": 6464254.1549641,
      "num_trades": 18432,
      "taker_buy_volume": 17.78283,
      "taker_buy_quote_volume": 1222429.419805
    },
    {
      "open_time": 1774201500000,
      "open": 68671.02,
      "high": 68741.16,
      "low": 68671.01,
      "close": 68673.02,
      "volume": 61.16858,
      "close_time": 1774202399999,
      "quote_volume": 4202777.449598,
      "num_trades": 16008,
      "taker_buy_volume": 22.87312,
      "taker_buy_quote_volume": 1571564.1085171
    },
    {
      "open_time": 1774202400000,
      "open": 68672.85,
      "high": 68720.92,
      "low": 68587.69,
      "close": 68720.91,
      "volume": 54.00703,
      "close_time": 1774203299999,
      "quote_volume": 3707740.6162308,
      "num_trades": 17415,
      "taker_buy_volume": 24.70251,
      "taker_buy_quote_volume": 1695877.6494904
    },
    {
      "open_time": 1774203300000,
      "open": 68720.91,
      "high": 68730.91,
      "low": 68662.77,
      "close": 68694.05,
      "volume": 39.73435,
      "close_time": 1774204199999,
      "quote_volume": 2729573.3934889,
      "num_trades": 10480,
      "taker_buy_volume": 14.42201,
      "taker_buy_quote_volume": 990692.4171879
    },
    {
      "open_time": 1774204200000,
      "open": 68694.04,
      "high": 68743.18,
      "low": 68344.57,
      "close": 68470.01,
      "volume": 190.55816,
      "close_time": 1774205099999,
      "quote_volume": 13054892.3788443,
      "num_trades": 43143,
      "taker_buy_volume": 63.77666,
      "taker_buy_quote_volume": 4369554.9831564
    },
    {
      "open_time": 1774205100000,
      "open": 68470.01,
      "high": 68619.51,
      "low": 68438.31,
      "close": 68618.58,
      "volume": 55.71764,
      "close_time": 1774205999999,
      "quote_volume": 3819261.794339,
      "num_trades": 16832,
      "taker_buy_volume": 31.74654,
      "taker_buy_quote_volume": 2176094.9559985
    },
    {
      "open_time": 1774206000000,
      "open": 68618.57,
      "high": 68626.07,
      "low": 68281.37,
      "close": 68332.16,
      "volume": 150.07873,
      "close_time": 1774206899999,
      "quote_volume": 10271089.3162247,
      "num_trades": 26109,
      "taker_buy_volume": 29.32068,
      "taker_buy_quote_volume": 2007169.7195549
    },
    {
      "open_time": 1774206900000,
      "open": 68332.15,
      "high": 68398.75,
      "low": 68275.0,
      "close": 68287.44,
      "volume": 91.52015,
      "close_time": 1774207799999,
      "quote_volume": 6255988.9530137,
      "num_trades": 22807,
      "taker_buy_volume": 52.45988,
      "taker_buy_quote_volume": 3585965.9407635
    },
    {
      "open_time": 1774207800000,
      "open": 68287.44,
      "high": 68424.09,
      "low": 68224.63,
      "close": 68390.24,
      "volume": 84.07995,
      "close_time": 1774208699999,
      "quote_volume": 5744717.7129664,
      "num_trades": 23490,
      "taker_buy_volume": 35.15877,
      "taker_buy_quote_volume": 2401976.8192884
    },
    {
      "open_time": 1774208700000,
      "open": 68390.24,
      "high": 68404.15,
      "low": 68145.01,
      "close": 68199.93,
      "volume": 147.31422,
      "close_time": 1774209599999,
      "quote_volume": 10053447.9764817,
      "num_trades": 26620,
      "taker_buy_volume": 40.88952,
      "taker_buy_quote_volume": 2789257.0166754
    },
    {
      "open_time": 1774209600000,
      "open": 68199.93,
      "high": 68369.3,
      "low": 68199.93,
      "close": 68335.88,
      "volume": 86.32667,
      "close_time": 1774210499999,
      "quote_volume": 5896769.9778434,
      "num_trades": 28054,
      "taker_buy_volume": 52.92231,
      "taker_buy_quote_volume": 3614890.9988899
    },
    {
      "open_time": 1774210500000,
      "open": 68335.88,
      "high": 68498.4,
      "low": 68274.67,
      "close": 68324.0,
      "volume": 75.62032,
      "close_time": 1774211399999,
      "quote_volume": 5170636.4065892,
      "num_trades": 23976,
      "taker_buy_volume": 34.39904,
      "taker_buy_quote_volume": 2352482.270381
    },
    {
      "open_time": 1774211400000,
      "open": 68324.23,
      "high": 68370.22,
      "low": 68194.0,
      "close": 68363.62,
      "volume": 64.59928,
      "close_time": 1774212299999,
      "quote_volume": 4411260.4083215,
      "num_trades": 22606,
      "taker_buy_volume": 34.69661,
      "taker_buy_quote_volume": 2369343.245298
    },
    {
      "open_time": 1774212300000,
      "open": 68363.62,
      "high": 68363.62,
      "low": 68080.0,
      "close": 68176.46,
      "volume": 92.98618,
      "close_time": 1774213199999,
      "quote_volume": 6341357.9027114,
      "num_trades": 33330,
      "taker_buy_volume": 31.22322,
      "taker_buy_quote_volume": 2129426.3330568
    },
    {
      "open_time": 1774213200000,
      "open": 68176.47,
      "high": 68228.71,
      "low": 67552.03,
      "close": 67780.83,
      "volume": 839.82399,
      "close_time": 1774214099999,
      "quote_volume": 56956300.8646243,
      "num_trades": 116763,
      "taker_buy_volume": 324.80948,
      "taker_buy_quote_volume": 22022586.0991712
    },
    {
      "open_time": 1774214100000,
      "open": 67780.83,
      "high": 67865.3,
      "low": 67360.66,
      "close": 67810.33,
      "volume": 472.52311,
      "close_time": 1774214999999,
      "quote_volume": 31922107.6576496,
      "num_trades": 95033,
      "taker_buy_volume": 211.21068,
      "taker_buy_quote_volume": 14273176.0702178
    },
    {
      "open_time": 1774215000000,
      "open": 67810.33,
      "high": 67984.15,
      "low": 67680.0,
      "close": 67874.82,
      "volume": 127.18863,
      "close_time": 1774215899999,
      "quote_volume": 8627643.8976071,
      "num_trades": 43075,
      "taker_buy_volume": 74.15106,
      "taker_buy_quote_volume": 5029552.8651675
    },
    {
      "open_time": 1774215900000,
      "open": 67874.82,
      "high": 67904.8,
      "low": 67761.11,
      "close": 67899.97,
      "volume": 95.9378,
      "close_time": 1774216799999,
      "quote_volume": 6507906.7179247,
      "num_trades": 41103,
      "taker_buy_volume": 51.93509,
      "taker_buy_quote_volume": 3522682.0076544
    },
    {
      "open_time": 1774216800000,
      "open": 67899.97,
      "high": 68135.14,
      "low": 67571.67,
      "close": 67912.81,
      "volume": 318.29944,
      "close_time": 1774217699999,
      "quote_volume": 21612392.9052434,
      "num_trades": 103804,
      "taker_buy_volume": 211.9018,
      "taker_buy_quote_volume": 14391147.5178243
    },
    {
      "open_time": 1774217700000,
      "open": 67912.81,
      "high": 68383.18,
      "low": 67864.0,
      "close": 68256.0,
      "volume": 291.88966,
      "close_time": 1774218599999,
      "quote_volume": 19880486.0732894,
      "num_trades": 76161,
      "taker_buy_volume": 185.7686,
      "taker_buy_quote_volume": 12651272.459222
    },
    {
      "open_time": 1774218600000,
      "open": 68256.0,
      "high": 68335.6,
      "low": 68099.82,
      "close": 68135.8,
      "volume": 154.91418,
      "close_time": 1774219499999,
      "quote_volume": 10570736.8069963,
      "num_trades": 55449,
      "taker_buy_volume": 65.17646,
      "taker_buy_quote_volume": 4447221.5358547
    },
    {
      "open_time": 1774219500000,
      "open": 68135.8,
      "high": 68396.94,
      "low": 68135.79,
      "close": 68339.37,
      "volume": 91.45772,
      "close_time": 1774220399999,
      "quote_volume": 6244400.4995883,
      "num_trades": 48104,
      "taker_buy_volume": 56.39667,
      "taker_buy_quote_volume": 3850210.9394112
    },
    {
      "open_time": 1774220400000,
      "open": 68339.38,
      "high": 68474.0,
      "low": 68200.01,
      "close": 68327.15,
      "volume": 115.75336,
      "close_time": 1774221299999,
      "quote_volume": 7908994.827373,
      "num_trades": 57275,
      "taker_buy_volume": 56.9611,
      "taker_buy_quote_volume": 3892341.3599444
    },
    {
      "open_time": 1774221300000,
      "open": 68327.15,
      "high": 68340.6,
      "low": 68103.06,
      "close": 68103.9,
      "volume": 132.27832,
      "close_time": 1774222199999,
      "quote_volume": 9026446.5979882,
      "num_trades": 45446,
      "taker_buy_volume": 74.36207,
      "taker_buy_quote_volume": 5075127.0521534
    },
    {
      "open_time": 1774222200000,
      "open": 68103.9,
      "high": 68161.47,
      "low": 67993.94,
      "close": 68126.67,
      "volume": 77.75528,
      "close_time": 1774223099999,
      "quote_volume": 5292294.7513407,
      "num_trades": 39037,
      "taker_buy_volume": 39.83822,
      "taker_buy_quote_volume": 2711749.510802
    },
    {
      "open_time": 1774223100000,
      "open": 68126.67,
      "high": 68145.6,
      "low": 67839.99,
      "close": 67859.0,
      "volume": 183.48931,
      "close_time": 1774223999999,
      "quote_volume": 12466334.0816301,
      "num_trades": 46175,
      "taker_buy_volume": 77.20068,
      "taker_buy_quote_volume": 5242959.7728391
    },
    {
      "open_time": 1774224000000,
      "open": 67859.0,
      "high": 68123.86,
      "low": 67779.33,
      "close": 67957.48,
      "volume": 305.76761,
      "close_time": 1774224899999,
      "quote_volume": 20775611.3385527,
      "num_trades": 76153,
      "taker_buy_volume": 177.54662,
      "taker_buy_quote_volume": 12061797.5813402
    },
    {
      "open_time": 1774224900000,
      "open": 67957.48,
      "high": 68161.41,
      "low": 67801.54,
      "close": 67994.06,
      "volume": 170.63,
      "close_time": 1774225799999,
      "quote_volume": 11599434.2233481,
      "num_trades": 66178,
      "taker_buy_volume": 101.51794,
      "taker_buy_quote_volume": 6901105.6132991
    },
    {
      "open_time": 1774225800000,
      "open": 67994.06,
      "high": 67999.94,
      "low": 67445.18,
      "close": 67689.52,
      "volume": 230.4121,
      "close_time": 1774226699999,
      "quote_volume": 15591313.2637222,
      "num_trades": 91894,
      "taker_buy_volume": 81.63663,
      "taker_buy_quote_volume": 5523355.9743519
    },
    {
      "open_time": 1774226700000,
      "open": 67689.52,
      "high": 67889.97,
      "low": 67619.89,
      "close": 67669.99,
      "volume": 116.88247,
      "close_time": 1774227599999,
      "quote_volume": 7916690.7245052,
      "num_trades": 61375,
      "taker_buy_volume": 59.17368,
      "taker_buy_quote_volume": 4008165.8926848
    }
  ],
  "candles_1h": [
    {
      "open_time": 1774137600000,
      "open": 68918.12,
      "high": 69155.86,
      "low": 68228.5,
      "close": 68954.71,
      "volume": 2161.16442,
      "close_time": 1774141199999,
      "quote_volume": 148582479.946055,
      "num_trades": 367565,
      "taker_buy_volume": 1101.38693,
      "taker_buy_quote_volume": 75739058.6889353
    },
    {
      "open_time": 1774141200000,
      "open": 68954.7,
      "high": 69100.0,
      "low": 68762.31,
      "close": 68962.4,
      "volume": 809.55651,
      "close_time": 1774144799999,
      "quote_volume": 55826958.6184656,
      "num_trades": 143545,
      "taker_buy_volume": 408.40998,
      "taker_buy_quote_volume": 28168959.954414
    },
    {
      "open_time": 1774144800000,
      "open": 68962.4,
      "high": 69411.1,
      "low": 68951.21,
      "close": 69278.12,
      "volume": 506.62838,
      "close_time": 1774148399999,
      "quote_volume": 35062455.402669,
      "num_trades": 136935,
      "taker_buy_volume": 295.53734,
      "taker_buy_quote_volume": 20453133.7726635
    },
    {
      "open_time": 1774148400000,
      "open": 69278.12,
      "high": 69588.79,
      "low": 69123.13,
      "close": 69339.99,
      "volume": 671.1404,
      "close_time": 1774151999999,
      "quote_volume": 46551314.3299314,
      "num_trades": 126421,
      "taker_buy_volume": 344.11045,
      "taker_buy_quote_volume": 23866710.4988547
    },
    {
      "open_time": 1774152000000,
      "open": 69340.0,
      "high": 69526.85,
      "low": 69215.89,
      "close": 69358.0,
      "volume": 626.75701,
      "close_time": 1774155599999,
      "quote_volume": 43467744.8603295,
      "num_trades": 92158,
      "taker_buy_volume": 378.67115,
      "taker_buy_quote_volume": 26263706.0945185
    },
    {
      "open_time": 1774155600000,
      "open": 69358.0,
      "high": 69358.0,
      "low": 69150.0,
      "close": 69153.41,
      "volume": 322.14134,
      "close_time": 1774159199999,
      "quote_volume": 22300123.3676617,
      "num_trades": 69460,
      "taker_buy_volume": 120.08091,
      "taker_buy_quote_volume": 8311424.6375514
    },
    {
      "open_time": 1774159200000,
      "open": 69153.41,
      "high": 69245.79,
      "low": 69059.87,
      "close": 69164.06,
      "volume": 378.08519,
      "close_time": 1774162799999,
      "quote_volume": 26142665.6098258,
      "num_trades": 71456,
      "taker_buy_volume": 173.24622,
      "taker_buy_quote_volume": 11978537.5824781
    },
    {
      "open_time": 1774162800000,
      "open": 69164.06,
      "high": 69250.08,
      "low": 68892.93,
      "close": 68919.38,
      "volume": 432.94301,
      "close_time": 1774166399999,
      "quote_volume": 29913547.40772,
      "num_trades": 88187,
      "taker_buy_volume": 187.53801,
      "taker_buy_quote_volume": 12959695.4787893
    },
    {
      "open_time": 1774166400000,
      "open": 68919.37,
      "high": 68990.67,
      "low": 68523.96,
      "close": 68804.77,
      "volume": 1053.77702,
      "close_time": 1774169999999,
      "quote_volume": 72448197.0630733,
      "num_trades": 151020,
      "taker_buy_volume": 411.86597,
      "taker_buy_quote_volume": 28323106.7918874
    },
    {
      "open_time": 1774170000000,
      "open": 68804.77,
      "high": 68901.65,
      "low": 68587.78,
      "close": 68826.2,
      "volume": 383.82763,
      "close_time": 1774173599999,
      "quote_volume": 26392580.3100595,
      "num_trades": 101810,
      "taker_buy_volume": 186.07681,
      "taker_buy_quote_volume": 12796875.3791612
    },
    {
      "open_time": 1774173600000,
      "open": 68826.21,
      "high": 68847.83,
      "low": 68584.27,
      "close": 68648.17,
      "volume": 360.03346,
      "close_time": 1774177199999,
      "quote_volume": 24736844.4503235,
      "num_trades": 83416,
      "taker_buy_volume": 185.92382,
      "taker_buy_quote_volume": 12772897.3472235
    },
    {
      "open_time": 1774177200000,
      "open": 68648.16,
      "high": 68691.03,
      "low": 68110.55,
      "close": 68217.95,
      "volume": 784.4316,
      "close_time": 1774180799999,
      "quote_volume": 53643521.3441214,
      "num_trades": 161951,
      "taker_buy_volume": 361.78492,
      "taker_buy_quote_volume": 24743723.1474894
    },
    {
      "open_time": 1774180800000,
      "open": 68217.94,
      "high": 68763.18,
      "low": 68199.04,
      "close": 68654.83,
      "volume": 484.243,
      "close_time": 1774184399999,
      "quote_volume": 33167690.1516101,
      "num_trades": 137952,
      "taker_buy_volume": 314.90531,
      "taker_buy_quote_volume": 21566881.8126425
    },
    {
      "open_time": 1774184400000,
      "open": 68654.83,
      "high": 68957.24,
      "low": 68548.32,
      "close": 68700.02,
      "volume": 548.07349,
      "close_time": 1774187999999,
      "quote_volume": 37687958.9033296,
      "num_trades": 120737,
      "taker_buy_volume": 306.87403,
      "taker_buy_quote_volume": 21101715.1945945
    },
    {
      "open_time": 1774188000000,
      "open": 68700.02,
      "high": 68915.27,
      "low": 68542.1,
      "close": 68711.66,
      "volume": 385.54476,
      "close_time": 1774191599999,
      "quote_volume": 26501930.1461422,
      "num_trades": 113564,
      "taker_buy_volume": 201.1362,
      "taker_buy_quote_volume": 13826561.6336786
    },
    {
      "open_time": 1774191600000,
      "open": 68711.66,
      "high": 69005.71,
      "low": 68700.0,
      "close": 68847.96,
      "volume": 391.17296,
      "close_time": 1774195199999,
      "quote_volume": 26931920.972406,
      "num_trades": 105167,
      "taker_buy_volume": 225.94324,
      "taker_buy_quote_volume": 15559377.0436996
    },
    {
      "open_time": 1774195200000,
      "open": 68847.97,
      "high": 68885.53,
      "low": 68665.62,
      "close": 68805.58,
      "volume": 258.25035,
      "close_time": 1774198799999,
      "quote_volume": 17758720.8148598,
      "num_trades": 66985,
      "taker_buy_volume": 128.42687,
      "taker_buy_quote_volume": 8831271.9330034
    },
    {
      "open_time": 1774198800000,
      "open": 68805.58,
      "high": 68848.32,
      "low": 68665.34,
      "close": 68673.02,
      "volume": 252.16281,
      "close_time": 1774202399999,
      "quote_volume": 17337039.1028039,
      "num_trades": 68536,
      "taker_buy_volume": 84.97551,
      "taker_buy_quote_volume": 5843691.7202469
    },
    {
      "open_time": 1774202400000,
      "open": 68672.85,
      "high": 68743.18,
      "low": 68344.57,
      "close": 68618.58,
      "volume": 340.01718,
      "close_time": 1774205999999,
      "quote_volume": 23311468.182903,
      "num_trades": 87870,
      "taker_buy_volume": 134.64772,
      "taker_buy_quote_volume": 9232220.0058332
    },
    {
      "open_time": 1774206000000,
      "open": 68618.57,
      "high": 68626.07,
      "low": 68145.01,
      "close": 68199.93,
      "volume": 472.99305,
      "close_time": 1774209599999,
      "quote_volume": 32325243.9586865,
      "num_trades": 99026,
      "taker_buy_volume": 157.82885,
      "taker_buy_quote_volume": 10784369.4962822
    },
    {
      "open_time": 1774209600000,
      "open": 68199.93,
      "high": 68498.4,
      "low": 68080.0,
      "close": 68176.46,
      "volume": 319.53245,
      "close_time": 1774213199999,
      "quote_volume": 21820024.6954655,
      "num_trades": 107966,
      "taker_buy_volume": 153.24118,
      "taker_buy_quote_volume": 10466142.8476257
    },
    {
      "open_time": 1774213200000,
      "open": 68176.47,
      "high": 68228.71,
      "low": 67360.66,
      "close": 67899.97,
      "volume": 1535.47353,
      "close_time": 1774216799999,
      "quote_volume": 104013959.1378057,
      "num_trades": 295974,
      "taker_buy_volume": 662.10631,
      "taker_buy_quote_volume": 44847997.0422109
    },
    {
      "open_time": 1774216800000,
      "open": 67899.97,
      "high": 68396.94,
      "low": 67571.67,
      "close": 68339.37,
      "volume": 856.561,
      "close_time": 1774220399999,
      "quote_volume": 58308016.2851174,
      "num_trades": 283518,
      "taker_buy_volume": 519.24353,
      "taker_buy_quote_volume": 35339852.4523122
    },
    {
      "open_time": 1774220400000,
      "open": 68339.38,
      "high": 68474.0,
      "low": 67839.99,
      "close": 67859.0,
      "volume": 509.27627,
      "close_time": 1774223999999,
      "quote_volume": 34694070.258332,
      "num_trades": 187933,
      "taker_buy_volume": 248.36207,
      "taker_buy_quote_volume": 16922177.6957389
    },
    {
      "open_time": 1774224000000,
      "open": 67859.0,
      "high": 68161.41,
      "low": 67445.18,
      "close": 67669.99,
      "volume": 823.69218,
      "close_time": 1774227599999,
      "quote_volume": 55883049.5501282,
      "num_trades": 295600,
      "taker_buy_volume": 419.87487,
      "taker_buy_quote_volume": 28494425.061676
    },
    {
      "open_time": 1774227600000,
      "open": 67670.0,
      "high": 68157.31,
      "low": 67536.01,
      "close": 67905.0,
      "volume": 628.21786,
      "close_time": 1774231199999,
      "quote_volume": 42680039.5446919,
      "num_trades": 227841,
      "taker_buy_volume": 309.02578,
      "taker_buy_quote_volume": 20994803.8254908
    },
    {
      "open_time": 1774231200000,
      "open": 67905.0,
      "high": 68400.0,
      "low": 67801.67,
      "close": 68320.72,
      "volume": 627.90507,
      "close_time": 1774234799999,
      "quote_volume": 42788203.2431608,
      "num_trades": 173508,
      "taker_buy_volume": 367.01686,
      "taker_buy_quote_volume": 25002480.5470148
    },
    {
      "open_time": 1774234800000,
      "open": 68320.72,
      "high": 68585.12,
      "low": 68059.88,
      "close": 68074.6,
      "volume": 415.80047,
      "close_time": 1774238399999,
      "quote_volume": 28383728.4971708,
      "num_trades": 148043,
      "taker_buy_volume": 191.92998,
      "taker_buy_quote_volume": 13101321.6890798
    },
    {
      "open_time": 1774238400000,
      "open": 68074.6,
      "high": 68550.0,
      "low": 68057.56,
      "close": 68541.0,
      "volume": 486.61149,
      "close_time": 1774241999999,
      "quote_volume": 33238892.4936148,
      "num_trades": 104776,
      "taker_buy_volume": 362.15043,
      "taker_buy_quote_volume": 24741089.7670708
    },
    {
      "open_time": 1774242000000,
      "open": 68541.0,
      "high": 68915.4,
      "low": 68541.0,
      "close": 68899.92,
      "volume": 1162.54953,
      "close_time": 1774245599999,
      "quote_volume": 79881933.7912627,
      "num_trades": 187688,
      "taker_buy_volume": 676.30235,
      "taker_buy_quote_volume": 46472773.6664655
    }
  ]
}